AUTHORS.rst
CONTRIBUTING.rst
HISTORY.rst
LICENSE
MANIFEST.in
README.rst
setup.cfg
setup.py
dbaas_flipper/__init__.py
dbaas_flipper/provider.py
dbaas_flipper.egg-info/PKG-INFO
dbaas_flipper.egg-info/SOURCES.txt
dbaas_flipper.egg-info/dependency_links.txt
dbaas_flipper.egg-info/not-zip-safe
dbaas_flipper.egg-info/top_level.txt