Metadata-Version: 1.1
Name: dbaas-flipper
Version: 0.0.1
Summary: Flipper integration 4 DBaaS
Home-page: https://github.com/felippemr/dbaas-flipper
Author: Felippe da Motta Raposo
Author-email: raposo.felippe@gmail.com
License: BSD
Keywords: dbaas_flipper
Platform: UNKNOWN
Classifier: Development Status :: 2 - Pre-Alpha
Classifier: Intended Audience :: Developers
Classifier: License :: OSI Approved :: BSD License
Classifier: Natural Language :: English
Classifier: Programming Language :: Python :: 2
Classifier: Programming Language :: Python :: 2.6
Classifier: Programming Language :: Python :: 2.7
Classifier: Programming Language :: Python :: 3
Classifier: Programming Language :: Python :: 3.3
